dummy_kinematics/__about__.py
dummy_kinematics/__init__.py
dummy_kinematics/chart_element.py
dummy_kinematics/config.py
dummy_kinematics/data_converter.py
dummy_kinematics/descriptors.py
dummy_kinematics/dummy_iso_config.py
dummy_kinematics/json_file_helper.py
dummy_kinematics/logger_helper.py
dummy_kinematics/ppt_factory.py
dummy_kinematics/ppt_insert_helper.py
dummy_kinematics/unitils.py
dummy_kinematics/default/default_template.pptx
dummy_kinematics-0.0.9.dist-info/METADATA
dummy_kinematics-0.0.9.dist-info/WHEEL
dummy_kinematics-0.0.9.dist-info/licenses/LICENSE.txt
dummy_kinematics-0.0.9.dist-info/RECORD
