Metadata-Version: 2.1
Name: dummy-kinematics
Version: 0.0.9
Project-URL: Documentation, https://github.com/unknown/dummy-kinematics#readme
Project-URL: Issues, https://github.com/unknown/dummy-kinematics/issues
Project-URL: Source, https://github.com/unknown/dummy-kinematics
Author-email: xiaochai <1219295581@qq.com>
License-Expression: MIT
License-File: LICENSE.txt
Classifier: Development Status :: 4 - Beta
Classifier: Programming Language :: Python
Classifier: Programming Language :: Python :: 3.11
Classifier: Programming Language :: Python :: Implementation :: CPython
Classifier: Programming Language :: Python :: Implementation :: PyPy
Requires-Python: >=3.11
Requires-Dist: colorama
Requires-Dist: numpy
Requires-Dist: openpyxl==3.1.0
Requires-Dist: pytest
Requires-Dist: pytest-cov
Requires-Dist: python-pptx
Requires-Dist: scipy
Requires-Dist: sqlalchemy-database
